examples/__init__.py
examples/send_test_event.py
scarf/__init__.py
scarf/event_logger.py
scarf/version.py
tests/__init__.py
tests/test_event_logger.py
scarf_sdk-0.1.1.dist-info/LICENSE
scarf_sdk-0.1.1.dist-info/METADATA
scarf_sdk-0.1.1.dist-info/WHEEL
scarf_sdk-0.1.1.dist-info/top_level.txt
scarf_sdk-0.1.1.dist-info/RECORD
