Metadata-Version: 2.1
Name: scarf-sdk
Version: 0.1.1
Summary: Python bindings for Scarf telemetry
Home-page: https://github.com/scarf-sh/scarf-py
Author: Scarf
Author-email: Scarf Engineering <engineering@scarf.sh>
Requires-Python: >=3.7
License-File: LICENSE
Requires-Dist: requests>=2.25.0
